{
    "subject": "CFP:: DIPECC- Dubai - Oct. 2013- UAE",
    "from": "\"The International Conference on Digital Information Processing, E-Business and Cloud Computing (DIPECC 2013)\" <donotreply@dcmrf.net>",
    "to": "foaad@calpoly.edu",
    "cc": null,
    "bcc": null,
    "date": "Mon, 05 Aug 2013 07:00:19 -0600",
    "body": "KIND REMINDER:: CALL for PAPERS and PARTICIPATION:: DIPECC- Dubai\nDeadline Submission: September 1, 2013\n\n==========================================================================\nThe International Conference on Digital Information Processing, E-Business and Cloud Computing (DIPECC 2013)\n                        Dubai, UAE\n                    October 23-25, 2013\n                       www.sdiwc.net\n\n===========================================================================\n\nThe proposed conference that will be held at Dubai, UAE From October 23-25, 2013 aims to enable researchers build connections between different digital applications.\n\nThe conference welcomes papers on the following (but not limited to) research topics:\n\n+ Biometrics Technologies\n+ Cloud Computing\n+ Cloud Engineering\n+ Cloud Gaming\n+ Cloud Security\n+ Computational Intelligence\n+ Computer Architecture and Design\n+ Cryptography and Data Protection\n+ Data Compression\n+ Data Embedding and Watermarking\n+ Data Management in Mobile Networks\n+ Data Stream Processing in Mobile/Sensor Networks\n+ Distributed and Parallel Applications\n+ E-Business\n+ E-Commerce Security\n+ E-Learning\n+ E-Technology\n+ Embedded Systems and Software\n+ Forensics, Recognition Technologies and Applications\n+ Fuzzy and Neural Network Systems\n+ Image Processing\n+ Information Content Security\n+ Information and Data Management\n+ Mobile Networking, Mobility and Nomadicity\n+ Mobile, Ad Hoc and Sensor Network Management\n+ Multimedia Computing\n+ Network Security\n+ Real-Time Systems\n+ Semantic Web and Ontologies\n+ Signal Processing, Pattern Recognition and Applications\n+ User Interface and Usability Issues for Mobile Applications\n+ User Interfaces, Visualization and Modeling\n+ Web Services Architecture, Modeling and Design\n+ Web Services Security\n+ Wireless Communications\n+ Wireless Sensor Networks\n\n\nResearchers are encouraged to submit their work electronically. All papers will be fully refereed by a minimum of two specialized referees. Before final acceptance, all referees comments must be considered. \n\n===========================================================================\n\nImportant Dates\n---------------\nSubmission Deadline       : September 1, 2013\nNotification of Acceptance: September 15, 2013\nCamera Ready Submission   : September 20, 2013\nRegistration              : September 20, 2013\nConference Dates          : October 23-25, 2013\n\n----------------------------------------\n\nIf you want to unsubscribe to this mail message from SDIWC, just follow this link http://dcmrf.net/Filemailer2/sdiwc-mailer/unsubscribe.php?id=65b73db1921a24fbe97786870799ab0b\n\n<html><head>\n<meta http-equiv=\"Content-Type\" content=\"text/html; charset=iso-8859-1\"></head><body>KIND REMINDER:: CALL for PAPERS and PARTICIPATION:: DIPECC- Dubai<br>\nDeadline Submission: September 1, 2013<br>\n<br>\n==========================================================================<br>\nThe International Conference on Digital Information Processing, E-Business and Cloud Computing (DIPECC 2013)<br>\n                        Dubai, UAE<br>\n                    October 23-25, 2013<br>\n                       www.sdiwc.net<br>\n<br>\n===========================================================================<br>\n<br>\nThe proposed conference that will be held at Dubai, UAE From October 23-25, 2013 aims to enable researchers build connections between different digital applications.<br>\n<br>\nThe conference welcomes papers on the following (but not limited to) research topics:<br>\n<br>\n&#43; Biometrics Technologies<br>\n&#43; Cloud Computing<br>\n&#43; Cloud Engineering<br>\n&#43; Cloud Gaming<br>\n&#43; Cloud Security<br>\n&#43; Computational Intelligence<br>\n&#43; Computer Architecture and Design<br>\n&#43; Cryptography and Data Protection<br>\n&#43; Data Compression<br>\n&#43; Data Embedding and Watermarking<br>\n&#43; Data Management in Mobile Networks<br>\n&#43; Data Stream Processing in Mobile/Sensor Networks<br>\n&#43; Distributed and Parallel Applications<br>\n&#43; E-Business<br>\n&#43; E-Commerce Security<br>\n&#43; E-Learning<br>\n&#43; E-Technology<br>\n&#43; Embedded Systems and Software<br>\n&#43; Forensics, Recognition Technologies and Applications<br>\n&#43; Fuzzy and Neural Network Systems<br>\n&#43; Image Processing<br>\n&#43; Information Content Security<br>\n&#43; Information and Data Management<br>\n&#43; Mobile Networking, Mobility and Nomadicity<br>\n&#43; Mobile, Ad Hoc and Sensor Network Management<br>\n&#43; Multimedia Computing<br>\n&#43; Network Security<br>\n&#43; Real-Time Systems<br>\n&#43; Semantic Web and Ontologies<br>\n&#43; Signal Processing, Pattern Recognition and Applications<br>\n&#43; User Interface and Usability Issues for Mobile Applications<br>\n&#43; User Interfaces, Visualization and Modeling<br>\n&#43; Web Services Architecture, Modeling and Design<br>\n&#43; Web Services Security<br>\n&#43; Wireless Communications<br>\n&#43; Wireless Sensor Networks<br>\n<br>\n<br>\nResearchers are encouraged to submit their work electronically. All papers will be fully refereed by a minimum of two specialized referees. Before final acceptance, all referees comments must be considered. <br>\n<br>\n===========================================================================<br>\n<br>\nImportant Dates<br>\n---------------<br>\nSubmission Deadline       : September 1, 2013<br>\nNotification of Acceptance: September 15, 2013<br>\nCamera Ready Submission   : September 20, 2013<br>\nRegistration              : September 20, 2013<br>\nConference Dates          : October 23-25, 2013   <br><br>If you want to unsubscribe to this mail message from SDIWC, just follow this link <a href=\"http://dcmrf.net/Filemailer2/sdiwc-mailer/unsubscribe.php?id=65b73db1921a24fbe97786870799ab0b\">http://dcmrf.net/Filemailer2/sdiwc-mailer/unsubscribe.php?id=65b73db1921a24fbe97786870799ab0b</a>\n\n\n</body></html>",
    "attachments": []
}