{
    "subject": "Welcomeshigh quality originalresearch papers",
    "from": "journal <journaloffice@yeah.net>",
    "to": "foaad@calpoly.edu",
    "cc": null,
    "bcc": null,
    "date": "Sat, 05 Oct 2019 10:38:49 +0000",
    "body": "Welcome to\n \nAJER\nSmooth, simple and timely publishing of review and research articles.\nAmerican Journal of Engineering Research\nWebsite\n:  \nwww.ajer.org\nEmail ID:\n \najer@editormails.com\neISSN : 2320-0847  pISSN : 2320-0936\n\n\n\n\n\n\n\n\n\n\n\n\n\n\n\n\n\n\nCALL FOR PAPERS\nLAST DATE OF SUBMISSION : 10- October 2019\nAcceptance Notification : Within 10 days\nManuscript Publication : Within 3 days after Registration\nA PEER REVIEWED REFEREED MONTHLY INTERNATIONAL JOURNAL\nCurrent Issue October, 2019 (Volume 08 - Issue 10)\n\n\n\n\n\n\n\n\nAll accepted papers from AJER 2019 will be published in the  \nAmerican journal of Engineering Research\n (online issue ISSN 2320-0847) (print issue ISSN 2320-0936)  (\nIndexed by\n Google Scholar, Ulrich Periodicals, EBSCO HOST, CSA, CAB Abstract, DOAJ)\nINDEXING List\nGoogle Scholar,\nJour Informatics,\nIndex Copernicus,\nCabells Directory,\nJ-Gate U.S.A,\nGoogle Scholar, \nDirectory of Open Journals (DOAJ),\nBielefeld Academic Search Engine,\nNew Jour,\nUlrichsweb.com (TM) -- The Global Source for Periodicals\nHydraulic Engineering,\nIndustrial Engineering,\nProduction and Operations Management,\nTotal Quality Management,\nMaterials and Mechanical Engineering,\nMining and Metallurgy,\nMilitary Science,\nTechnology in General,\nTransportation,\nChemical Technology,\nComputer Science,\nSoftware Engineering,\nConstruction,\nElectrical and Nuclear Engineering,\nEnvironmental Engineering,\nEnvironmental Technology,\nGeneral and Civil Engineering,\nProcess Engineering.\n(\nInternational Journal\n)\nFeatures & Benefits of AJER Authors:\nFast & Easy paper publishing process.\nAJER provides individual \n\nAmerican National Engineering Database (ANED)\n\n number to every article.\nAJER provides individual \n\nDigitally Signed E-Certificate\n\n to all Authors.\nAuthors are required to submit the full paper (PDF and Word format) to the  ajer@editormails.com\n\n\n\n\n\n\n\n\nONLINE PAPER SUBMISSION\n\n\n\n\n\n\n\n\nAJER Journal: PROMISING QUICK AND QUALITY PUBLICATION\n----------\n\n\n\n\n\n\n\n\n\n\n\n\n\n\n\n\n\n\n\n\n\n\n\n                            ajer, ajer, journal 123432, Vietnam\n                        \n\n\n\n\n\n\n\n\n\n\n\n                            Bn c th \n                            \nhy ng k\n\n                             hoc \n                            \nthay i thng tin ca bn\n\n                             bt c lc no.\n                        \n\n\n\n\n\n\n\n\n\n\n\n\n\n\n\n\n\n\n\n\nCung cp bi:",
    "attachments": []
}